{
  "clients": [
    {
      "name": "Drew",
      "agentName": "Drew's Agent",
      "ip": "100.124.57.91",
      "dashboardUrl": "",
      "status": "healthy",
      "gatewayRunning": true,
      "lastHeartbeat": "",
      "uptime": "15:50  up 2 days,  7:07, 2 users, load averages: 1.61 1.66 1",
      "disk": "",
      "errors": 0
    },
    {
      "name": "Darryl",
      "agentName": "Brit",
      "ip": "100.83.184.91",
      "dashboardUrl": "https://solveworks.io/darryl/",
      "status": "healthy",
      "gatewayRunning": true,
      "lastHeartbeat": "",
      "uptime": "11:50  up 1 day, 21:44, 1 user, load averages: 1.37 1.57 1.6",
      "disk": "",
      "errors": 0
    }
  ],
  "timestamp": "2026-02-23T15:50:08.069553"
}
