{
  "items": [
    {"title": "The Hard Thing About Hard Things", "author": "Ben Horowitz", "type": "Book", "status": "reading", "progress": 64, "note": "Recommended by board member. Great chapter on CEO psychology."},
    {"title": "AI Agents Will Reshape Enterprise Software", "author": "Stratechery", "type": "Article", "status": "queued", "url": "#", "note": "Relevant to our thesis. Share with investors."},
    {"title": "Zero to One", "author": "Peter Thiel", "type": "Book", "status": "completed", "progress": 100, "note": "Re-read. Refreshed thinking on monopoly theory for pitch deck."},
    {"title": "The State of AI 2026", "author": "Nathan Benaich", "type": "Report", "status": "queued", "url": "#", "note": "Annual report. Use data points for board presentation."},
    {"title": "How Stripe Built a $95B Company", "author": "The Generalist", "type": "Article", "status": "reading", "progress": 30, "note": "Studying their partnership-led growth model."}
  ]
}
